LICENSE.txt
MANIFEST.in
README.rst
setup.cfg
setup.py
frimcla/Comparing.py
frimcla/StatisticalComparison.py
frimcla/__init__.py
frimcla/command_line.py
frimcla/comparebest.py
frimcla/fullAnalysis.py
frimcla/graficaComparativa.py
frimcla/h5py2csv.py
frimcla/index_features.py
frimcla/malaria2000.py
frimcla/prediction.py
frimcla/train.py
frimcla.egg-info/PKG-INFO
frimcla.egg-info/SOURCES.txt
frimcla.egg-info/dependency_links.txt
frimcla.egg-info/entry_points.txt
frimcla.egg-info/requires.txt
frimcla.egg-info/top_level.txt
frimcla/DenseNet/__init__.py
frimcla/DenseNet/cifar10.py
frimcla/DenseNet/cifar100.py
frimcla/DenseNet/densenet.py
frimcla/DenseNet/densenet_fast.py
frimcla/DenseNet/imagenet_inference.py
frimcla/DenseNet/subpixel.py
frimcla/DenseNet/tensorflow_backend.py
frimcla/DenseNet/theano_backend.py
frimcla/DenseNet/weights/__init__.py
frimcla/DenseNet/weights/weight_translation_121.py
frimcla/DenseNet/weights/weight_translation_161.py
frimcla/DenseNet/weights/weight_translation_169.py
frimcla/StatisticalAnalysis/__init__.py
frimcla/StatisticalAnalysis/multiprocessingTests.py
frimcla/StatisticalAnalysis/statisticalAnalysis.py
frimcla/StatisticalAnalysis/stac/__init__.py
frimcla/StatisticalAnalysis/stac/nonparametric_tests.py
frimcla/StatisticalAnalysis/stac/parametric_tests.py
frimcla/StatisticalAnalysis/stac/unit_tests.py
frimcla/StatisticalAnalysis/stac/doc/__init__.py
frimcla/StatisticalAnalysis/stac/doc/build/genindex.html
frimcla/StatisticalAnalysis/stac/doc/build/homocedasticity.html
frimcla/StatisticalAnalysis/stac/doc/build/index.html
frimcla/StatisticalAnalysis/stac/doc/build/nonparametric.html
frimcla/StatisticalAnalysis/stac/doc/build/nonparametric_multi.html
frimcla/StatisticalAnalysis/stac/doc/build/nonparametric_two.html
frimcla/StatisticalAnalysis/stac/doc/build/normality.html
frimcla/StatisticalAnalysis/stac/doc/build/parametric.html
frimcla/StatisticalAnalysis/stac/doc/build/parametric_multi.html
frimcla/StatisticalAnalysis/stac/doc/build/parametric_two.html
frimcla/StatisticalAnalysis/stac/doc/build/scipy-stats.html
frimcla/StatisticalAnalysis/stac/doc/build/scipy.stats.kstest.html
