Metadata-Version: 1.1
Name: frimcla
Version: 1.0.4
Summary: Framework for Image Classification using traditional and deep learning techniques
Home-page: https://github.com/manugar/frimcla
Author: Manuel Garcia
Author-email: magarcd@unirioja.es
License: UNKNOWN
Keywords: image classification,classification,transfer learning,feature extractor,neural network,deep learning
Platform: UNKNOWN
Classifier: Development Status :: 4 - Beta
Classifier: Intended Audience :: Developers
Classifier: Topic :: Software Development :: Build Tools
Classifier: License :: OSI Approved :: MIT License
Classifier: Programming Language :: Python :: 3
Classifier: Programming Language :: Python :: 3.6
